setup.planblick.autorun.py
planblick.autorun.egg-info/PKG-INFO
planblick.autorun.egg-info/SOURCES.txt
planblick.autorun.egg-info/dependency_links.txt
planblick.autorun.egg-info/not-zip-safe
planblick.autorun.egg-info/requires.txt
planblick.autorun.egg-info/top_level.txt
planblick/autorun/__init__.py
planblick/autorun/autorun.py