Metadata-Version: 1.0
Name: planblick.autorun
Version: 0.0.11
Summary: A simple class that can be placed in a services root folder and will be picked up and executed during deployment
Home-page: https://www.planblick.com
Author: Florian Kröber @ Planblick
Author-email: fk@planblick.com
License: MIT
Platform: UNKNOWN
